dictpath_resolver/__init__.py
dictpath_resolver/exceptions.py
dictpath_resolver/resolver.py
dictpath_resolver-0.0.1.dist-info/LICENSE
dictpath_resolver-0.0.1.dist-info/WHEEL
dictpath_resolver-0.0.1.dist-info/METADATA
dictpath_resolver-0.0.1.dist-info/RECORD
