Metadata-Version: 2.1
Name: dictpath_resolver
Version: 0.0.1
Summary: Provides a simple syntax to access nested JSON-like object in python.
Author-email: Shaokun Xie <shaokun.xie@outlook.fr>
Requires-Python: >=3.6
Classifier: License :: OSI Approved :: GNU General Public License v3 or later (GPLv3+)
